rulea/__init__.py
rulea/action_registry.py
rulea/cli.py
rulea/engine.py
rulea/evaluator.py
rulea/model.py
rulea/parser.py
rulea/stdlib.py
rulea-1.1.2.dist-info/licenses/LICENSE
rulea-1.1.2.dist-info/METADATA
rulea-1.1.2.dist-info/WHEEL
rulea-1.1.2.dist-info/entry_points.txt
rulea-1.1.2.dist-info/top_level.txt
rulea-1.1.2.dist-info/RECORD
