Metadata-Version: 2.4
Name: rulea
Version: 1.1.2
Summary: Rule-based programmable language in Python
Home-page: https://github.com/tanuki276/rulea
Author: tanuki276
Author-email: soln <you@example.com>
License: MIT
Classifier: Programming Language :: Python :: 3
Classifier: License :: OSI Approved :: MIT License
Classifier: Operating System :: OS Independent
Requires-Python: >=3.8
License-File: LICENSE
Dynamic: license-file
